living_doc_utilities/__init__.py
living_doc_utilities/constants.py
living_doc_utilities/decorators.py
living_doc_utilities/logging_config.py
living_doc_utilities/py.typed
living_doc_utilities/exporter/__init__.py
living_doc_utilities/exporter/exporter.py
living_doc_utilities/factory/__init__.py
living_doc_utilities/factory/issue_factory.py
living_doc_utilities/github/__init__.py
living_doc_utilities/github/rate_limiter.py
living_doc_utilities/github/utils.py
living_doc_utilities/inputs/__init__.py
living_doc_utilities/inputs/action_inputs.py
living_doc_utilities/model/__init__.py
living_doc_utilities/model/feature_issue.py
living_doc_utilities/model/functionality_issue.py
living_doc_utilities/model/issue.py
living_doc_utilities/model/issues.py
living_doc_utilities/model/project_status.py
living_doc_utilities/model/user_story_issue.py
living_doc_utilities-0.3.1.dist-info/licenses/LICENSE
living_doc_utilities-0.3.1.dist-info/METADATA
living_doc_utilities-0.3.1.dist-info/WHEEL
living_doc_utilities-0.3.1.dist-info/top_level.txt
living_doc_utilities-0.3.1.dist-info/RECORD
