Metadata-Version: 2.4
Name: living-doc-utilities
Version: 0.3.1
Summary: Core utility functions and data models shared across the living-doc ecosystem.
Author-email: Miroslav Pojer <miroslav.pojer@absa.africa>
License-Expression: Apache-2.0
Project-URL: Repository, https://github.com/AbsaOSS/living-doc-utilities
Requires-Python: >=3.12
License-File: LICENSE
Dynamic: license-file
